lib4relind/__init__.py
sm4relind-1.0.5.dist-info/LICENSE
sm4relind-1.0.5.dist-info/METADATA
sm4relind-1.0.5.dist-info/WHEEL
sm4relind-1.0.5.dist-info/top_level.txt
sm4relind-1.0.5.dist-info/RECORD
