Metadata-Version: 2.1
Name: sm4relind
Version: 1.0.5
Summary: A set of functions to control Sequent Microsystems 4-Relay board
Home-page: https://www.sequentmicrosystems.com
Author: Sequent Microsystems
Author-email: olcitu@gmail.com
License: MIT
Classifier: License :: OSI Approved :: MIT License
Classifier: Operating System :: OS Independent
Classifier: Programming Language :: Python :: 2.7
Classifier: Programming Language :: Python :: 3
Classifier: Programming Language :: Python :: 3.4
Classifier: Programming Language :: Python :: 3.5
Classifier: Programming Language :: Python :: 3.6
Classifier: Programming Language :: Python :: 3.7
License-File: LICENSE
Requires-Dist: smbus2
